segdb/__init__.py
segdb/lookup.py
segdb/classes/Color.py
segdb/classes/DB.py
segdb/classes/Segment.py
segdb/classes/Triplet.py
segdb/classes/__init__.py
segdb/data/categories.csv
segdb/data/modifiers.csv
segdb/data/segmentations.csv
segdb/data/types.csv
segdb/tools/__init__.py
segdb/tools/dcmqi_config_generator.py
segdb/tools/generator.py
segdb/tools/generator2.py
segdb/tools/importer.py
segdb/tools/segdb_navigator.py
ymldicomseg/__init__.py
ymldicomseg/ymldicomseg.py
ymldicomseg/data/categories.csv
ymldicomseg/data/modifyers.csv
ymldicomseg/data/segmentations.csv
ymldicomseg/data/types.csv
segdb-0.0.3.dist-info/METADATA
segdb-0.0.3.dist-info/WHEEL
segdb-0.0.3.dist-info/top_level.txt
segdb-0.0.3.dist-info/RECORD
