Metadata-Version: 2.1
Name: segdb
Version: 0.0.3
Summary: Database for uniform body segmentation.
Home-page: https://github.com/MHubAI/SegDB
Author: Leonard Nürnberg
Author-email: lnuernberg@bwh.harvard.edu
License: MIT
Keywords: mhub
Classifier: Development Status :: 4 - Beta
Classifier: Topic :: Software Development :: Libraries :: Python Modules
Classifier: License :: OSI Approved :: MIT License
Requires-Dist: pandas
